chemkin_grp11/__init__.py
chemkin_grp11-0.1.1.dist-info/DESCRIPTION.rst
chemkin_grp11-0.1.1.dist-info/METADATA
chemkin_grp11-0.1.1.dist-info/RECORD
chemkin_grp11-0.1.1.dist-info/WHEEL
chemkin_grp11-0.1.1.dist-info/metadata.json
chemkin_grp11-0.1.1.dist-info/top_level.txt
